{
    "id": "UCP_pt1pW5vWstbhY8br2U0A",
    "header": {
        "name": "Shiori Ch. 菊理しおり【HKvtuber】",
        "image": "https://yt3.ggpht.com/gmxMVMM9SU-7im5y07U3gG8-xw6ctbKkwyDLunsESZmk_CdCy91xPtc8lLewrsFsf7hfJzRjBg=s88-c-k-c0x00ffffff-no-rj",
        "bg": ""
    },
    "body": [
        {
            "type": "title_content",
            "data": {
                "title": "描述",
                "content": "content"
            }
        },
        {
            "type": "title_map",
            "data": {
                "title": "Info",
                "map_list": [
                    {
                        "key": "生日",
                        "content": ""
                    },
                    {
                        "key": "愛好",
                        "content": ""
                    },
                    {
                        "key": "其他",
                        "content": "xxxxx"
                    }
                ]
            }
        },
        {
            "type": "title_contact",
            "data": {
                "title": "更多聯絡方式",
                "content": [
                    {
                        "key": "youtube",
                        "path": "UCP_pt1pW5vWstbhY8br2U0A"
                    },
                    {
                        "key": "twitter",
                        "path": ""
                    }
                ]
            }
        },
        {
            "type": "title_youtube",
            "data": {
                "title": "推薦",
                "video_list": [
                    {
                        "video_code": "",
                        "image": "",
                        "title": "",
                        "author": ""
                    }
                ]
            }
        }
    ]
}
